password_generator/__init__.py
password_generator/generate_password.py
tests/__init__.py
tests/test_generator.py
password_generator_hoka-0.0.3.dist-info/LICENSE
password_generator_hoka-0.0.3.dist-info/METADATA
password_generator_hoka-0.0.3.dist-info/WHEEL
password_generator_hoka-0.0.3.dist-info/entry_points.txt
password_generator_hoka-0.0.3.dist-info/top_level.txt
password_generator_hoka-0.0.3.dist-info/RECORD
