Metadata-Version: 2.1
Name: password-generator-hoka
Version: 0.0.3
Home-page: https://github.com/HoKa03/password-generator
Author: Oybek
Author-email: tolqinovoybek92@gmail.com
Classifier: Programming Language :: Python :: 3
Classifier: License :: OSI Approved :: MIT License
Classifier: Operating System :: OS Independent
Requires-Python: >=3.6
License-File: LICENSE
